aiagentaz/__init__.py
aiagentaz/core/chain.py
aiagentaz/core/clients.py
aiagentaz/core/request.py
aiagentaz/core/graph/abc.py
aiagentaz/core/graph/node.py
aiagentaz/domain/__init__.py
aiagentaz/domain/agent.py
aiagentaz/domain/agent.pyi
aiagentaz/domain/chain.py
aiagentaz/domain/chain.pyi
aiagentaz/domain/clients/anthropic.py
aiagentaz/domain/clients/anthropic.pyi
aiagentaz/domain/clients/gemini.py
aiagentaz/domain/clients/gemini.pyi
aiagentaz/domain/clients/openai.py
aiagentaz/domain/clients/openai.pyi
aiagentaz/domain/graph/operators/basicoperator.py
aiagentaz-0.2.0.dist-info/licenses/LICENSE
aiagentaz-0.2.0.dist-info/METADATA
aiagentaz-0.2.0.dist-info/WHEEL
aiagentaz-0.2.0.dist-info/top_level.txt
aiagentaz-0.2.0.dist-info/RECORD
